setup.cfg
setup.py
datapub/Datapub.py
datapub/__init__.py
datapub.egg-info/PKG-INFO
datapub.egg-info/SOURCES.txt
datapub.egg-info/dependency_links.txt
datapub.egg-info/not-zip-safe
datapub.egg-info/requires.txt
datapub.egg-info/top_level.txt