Metadata-Version: 1.1
Name: datapub
Version: 0.0.1
Summary: Python bindings for datapub.io web API
Home-page: UNKNOWN
Author: Jeff Workman
Author-email: jeff.workman@gmail.com
License: MIT
Keywords: datapub
Platform: UNKNOWN
Classifier: Development Status :: 3 - Alpha
Classifier: License :: OSI Approved :: MIT License
Classifier: Programming Language :: Python :: 3
